MasteringDjangoCore/README.md
MasteringDjangoCore/__init__.py
MasteringDjangoCore/__main__.py
MasteringDjangoCore/file.epub
MasteringDjangoCore/index.html
MasteringDjangoCore/css/__init__.py
MasteringDjangoCore/css/annotations.css
MasteringDjangoCore/css/main.css
MasteringDjangoCore/css/normalize.css
MasteringDjangoCore/css/popup.css
MasteringDjangoCore/font/__init__.py
MasteringDjangoCore/font/fontello.eot
MasteringDjangoCore/font/fontello.svg
MasteringDjangoCore/font/fontello.ttf
MasteringDjangoCore/font/fontello.woff
MasteringDjangoCore/img/__init__.py
MasteringDjangoCore/img/annotator-glyph-sprite.png
MasteringDjangoCore/img/annotator-icon-sprite.png
MasteringDjangoCore/img/apple-touch-icon.png
MasteringDjangoCore/img/cancelfullscreen.png
MasteringDjangoCore/img/close.png
MasteringDjangoCore/img/fullscreen.png
MasteringDjangoCore/img/loader.gif
MasteringDjangoCore/img/menu-icon.png
MasteringDjangoCore/img/save.png
MasteringDjangoCore/img/saved.png
MasteringDjangoCore/img/settings-s.png
MasteringDjangoCore/img/settings.png
MasteringDjangoCore/img/star.png
MasteringDjangoCore/js/__init__.py
MasteringDjangoCore/js/epub.js
MasteringDjangoCore/js/epub.min.js
MasteringDjangoCore/js/epub.min.map
MasteringDjangoCore/js/hooks.min.js
MasteringDjangoCore/js/hooks.min.map
MasteringDjangoCore/js/reader.js
MasteringDjangoCore/js/reader.js.map
MasteringDjangoCore/js/reader.min.js
MasteringDjangoCore/js/reader.min.map
MasteringDjangoCore/js/hooks/__init__.py
MasteringDjangoCore/js/hooks/extensions/__init__.py
MasteringDjangoCore/js/hooks/extensions/highlight.js
MasteringDjangoCore/js/libs/__init__.py
MasteringDjangoCore/js/libs/jquery.min.js
MasteringDjangoCore/js/libs/localforage.min.js
MasteringDjangoCore/js/libs/screenfull.js
MasteringDjangoCore/js/libs/screenfull.min.js
MasteringDjangoCore/js/libs/zip.min.js
MasteringDjangoCore/js/plugins/__init__.py
MasteringDjangoCore/js/plugins/hypothesis.js
MasteringDjangoCore/js/plugins/search.js
mastering_django_core-2024.3.2.0.dist-info/METADATA
mastering_django_core-2024.3.2.0.dist-info/WHEEL
mastering_django_core-2024.3.2.0.dist-info/entry_points.txt
mastering_django_core-2024.3.2.0.dist-info/top_level.txt
mastering_django_core-2024.3.2.0.dist-info/RECORD
